{"info": {"num_results": 331, "limit": 100, "offset": 0, "query": "thriller", "type": "album", "page": 1}, "albums": [{"name": "Thriller 25 Super Deluxe Edition", "popularity": "0.77", "external-ids": [{"type": "upc", "id": "888880436030"}], "href": "spotify:album:1C2h7mLntPSeVYciMRTF4a", "artists": [{"href": "spotify:artist:3fMbdgg4jU18AjLCKBhRSm", "name": "Michael Jackson"}], "availability": {"territories": "AD AR AT AU BE BG BO BR CA CH CL CO CR CY CZ DE DK DO EC EE ES FI FR GB GR GT HK HN HR HU IE IS IT LI LT LU LV MC MT MX MY NI NL NO NZ PA PE PH PL PT PY RO SE SG SI SK SV TR TW US UY"}}, {"name": "Thriller", "popularity": "0.6", "external-ids": [{"type": "upc", "id": "074643811224"}], "href": "spotify:album:2ANVost0y2y52ema1E9xAZ", "artists": [{"href": "spotify:artist:3fMbdgg4jU18AjLCKBhRSm", "name": "Michael Jackson"}], "availability": {"territories": "US"}}, {"name": "Thriller", "popularity": "0.35", "external-ids": [{"type": "upc", "id": "00602537567195"}], "href": "spotify:album:5dO1HV7j4r8xbDRApCql7l", "artists": [{"href": "spotify:artist:2hcsKca6hCfFMwwdbFvenJ", "name": "BTOB"}], "availability": {"territories": "AT AU BE BR CL CO CY CZ DE DK DO EC EE ES FI FR GB HK HR HU IE IS IT LT LU LV MY NL NO NZ PE PH PL PT SE SG SI SK TR TW"}}, {"name": "Thriller", "popularity": "0.34", "external-ids": [{"type": "upc", "id": "00602537567195"}], "href": "spotify:album:5GWF4P5HCrjEnpLE96oTat", "artists": [{"href": "spotify:artist:2hcsKca6hCfFMwwdbFvenJ", "name": "BTOB"}], "availability": {"territories": "CA MX US"}}, {"name": "Thriller", "popularity": "0.31", "external-ids": [{"type": "upc", "id": "9399700091946"}], "href": "spotify:album:6JwMaTXGhIORvOXpOotryr", "artists": [{"href": "spotify:artist:3fMbdgg4jU18AjLCKBhRSm", "name": "Michael Jackson"}], "availability": {"territories": "CA"}}, {"name": "Epic Thriller Hybrids", "popularity": "0.34", "external-ids": [{"type": "upc", "id": "5055807395533"}], "href": "spotify:album:0XkEBMIx543SvYOVSPbUOf", "artists": [{"href": "spotify:artist:3BRizPspINkIYljgzP1x6J", "name": "Oliver Davis"}], "availability": {"territories": "AD AR AT AU BE BG BO BR CA CH CL CO CR CY CZ DE DK DO EC EE ES FI FR GB GR GT HK HN HR HU IE IS IT LI LT LU LV MC MT MX MY NI NL NO NZ PA PE PH PL PT PY RO SE SG SI SK SV TR TW US UY"}}, {"name": "Thriller", "popularity": "0.28", "external-ids": [{"type": "upc", "id": "816769018824"}], "href": "spotify:album:4XmCkAEQGL5ZyStOecIpyb", "artists": [{"href": "spotify:artist:3QryVD03gGZOLQQXjy3EoA", "name": "Getter"}], "availability": {"territories": "AD AR AT AU BE BG BO BR CA CH CL CO CR CY CZ DE DK DO EC EE ES FI FR GB GR GT HK HN HR HU IE IS IT LI LT LU LV MC MT MX MY NI NL NO NZ PA PE PH PL PT PY RO SE SG SI SK SV TR TW US UY"}}, {"name": "Thriller \/ Heads Will Roll (Glee Cast Version)", "popularity": "0.37", "external-ids": [{"type": "upc", "id": "884977904437"}], "href": "spotify:album:3R90snrrOlsz5wzsMzMq7e", "artists": [{"href": "spotify:artist:0SCbttzoZTnLFebDYmAWCm", "name": "Glee Cast"}], "availability": {"territories": "AD AT AU BR CA CH DE EE ES FI FR GB IE LI LT LV MC MX NL NZ PH PL SG US"}}, {"name": "Thriller (Alben f\u00fcr die Ewigkeit)", "popularity": "0.35", "external-ids": [{"type": "upc", "id": "886443814479"}], "href": "spotify:album:1oPm66d5C3tP6CtMvRTaXR", "artists": [{"href": "spotify:artist:3fMbdgg4jU18AjLCKBhRSm", "name": "Michael Jackson"}], "availability": {"territories": "AT CH DE LI"}}, {"name": "Thriller!", "popularity": "0.26", "external-ids": [{"type": "upc", "id": "081227637064"}], "href": "spotify:album:0p2lWjdvrFrqhUTgX2W2d4", "artists": [{"href": "spotify:artist:0q8LQM9bH2uGZ9QvA3NeZO", "name": "Cold Blood"}], "availability": {"territories": "AD AR AT AU BE BG BO BR CA CH CL CO CR CY CZ DE DK DO EC EE ES FI FR GB GR GT HK HN HR HU IE IS IT LI LT LU LV MC MT MX MY NI NL NO NZ PA PE PH PL PT PY RO SE SG SI SK SV TR TW US UY"}}, {"name": "Thriller", "popularity": "0.01", "external-ids": [{"type": "upc", "id": "776098134629"}], "href": "spotify:album:2OTGKklz492RBEv8mvymbj", "artists": [{"href": "spotify:artist:3CiY0RnS9K2BLGUMqzqtPa", "name": "Thriller"}], "availability": {"territories": "AD AR AT AU BE BG BO BR CA CH CL CO CR CY CZ DE DK DO EC EE ES FI FR GB GR GT HK HN HR HU IE IS IT LI LT LU LV MC MT MX MY NI NL NO NZ PA PE PH PL PT PY RO SE SG SI SK SV TR TW US UY"}}, {"name": "Thriller Jazz (Jazz Club)", "popularity": "0.28", "external-ids": [{"type": "upc", "id": "00602498374399"}], "href": "spotify:album:3PBEMIhUUqHs75tWjekVvt", "artists": [{"name": "Various Artists"}], "availability": {"territories": "AR AT AU BE BG BR CL CO CR CZ DE DK EE ES FI FR GB GR HK HR HU IE IT LT LU LV MY NL NO NZ PH PL PT RO SE SG SI SK TR TW"}}, {"name": "Music in the Russian thriller movie", "popularity": "0.29", "external-ids": [{"type": "upc", "id": "5060252581271"}], "href": "spotify:album:6VFUtlQ1soKDiJUAPsPEU4", "artists": [{"name": "Various Artists"}], "availability": {"territories": "AD AR AT AU BE BG BO BR CA CH CL CO CR CY CZ DE DK DO EC EE ES FI FR GB GR GT HK HN HR HU IE IS IT LI LT LU LV MC MT MX MY NI NL NO NZ PA PE PH PL PT PY RO SE SG SI SK SV TR TW US UY"}}, {"name": "Thriller", "popularity": "0.19", "external-ids": [{"type": "upc", "id": "5051083046640"}, {"type": "upc", "id": "5051083046640"}], "href": "spotify:album:16xcnFIBnzhGP6u6apl5Ss", "artists": [{"href": "spotify:artist:7E5T06seybp7KCxaac22jz", "name": "Part Chimp"}], "availability": {"territories": "AD AR AT AU BE BG BO BR CA CH CL CO CR CY CZ DE DK DO EC EE ES FI FR GB GR GT HK HN HR HU IE IS IT LI LT LU LV MC MT MX MY NI NL NO NZ PA PE PH PL PT PY RO SE SG SI SK SV TR TW US UY"}}, {"name": "Metal Thriller", "popularity": "0.23", "external-ids": [{"type": "upc", "id": "889176400094"}], "href": "spotify:album:0VoKFDRAu9zG4BEkmq57xg", "artists": [{"name": "Various Artists"}], "availability": {"territories": "AD AR AT AU BE BG BO BR CA CH CL CO CR CY CZ DE DK DO EC EE ES FI FR GB GR GT HK HN HR HU IE IS IT LI LT LU LV MC MT MX MY NI NL NO NZ PA PE PH PL PT PY RO SE SG SI SK SV TR TW US UY"}}, {"name": "Spy Thriller", "popularity": "0.23", "external-ids": [{"type": "upc", "id": "888002758224"}], "href": "spotify:album:5Q5VtK3EOr4KsnoXGWZaQC", "artists": [{"href": "spotify:artist:4rYrx8z5qitke4axuq8kKY", "name": "Das Kabinette"}], "availability": {"territories": "AD AR AT AU BE BG BO BR CA CH CL CO CR CY CZ DE DK DO EC EE ES FI FR GB GR GT HK HN HR HU IE IS IT LI LT LU LV MC MT MX MY NI NL NO NZ PA PE PH PL PT PY RO SE SG SI SK SV TR TW US UY"}}, {"name": "Thriller", "popularity": "0.15", "external-ids": [{"type": "upc", "id": "792258106268"}], "href": "spotify:album:1dkoxDB7s4CvMUvMwqc0wX", "artists": [{"href": "spotify:artist:5NJRExT7VDHWYQTPPoUurl", "name": "New End Original"}], "availability": {"territories": "AD AR AT AU BE BG BO BR CA CH CL CO CR CY CZ DE DK DO EC EE ES FI FR GB GR GT HK HN HR HU IE IS IT LI LT LU LV MC MT MX MY NI NL NO NZ PA PE PH PL PT PY RO SE SG SI SK SV TR TW UY"}}, {"name": "Thriller", "popularity": "0.15", "external-ids": [{"type": "upc", "id": "792258106268"}], "href": "spotify:album:0Ce13JDvdvMjQPCCsawKYA", "artists": [{"href": "spotify:artist:5NJRExT7VDHWYQTPPoUurl", "name": "New End Original"}], "availability": {"territories": "US"}}, {"name": "Thriller", "popularity": "0.15", "external-ids": [{"type": "upc", "id": "8715576157684"}], "href": "spotify:album:5x1GEXZjdffxijRgkJ4GLn", "artists": [{"href": "spotify:artist:7taXPPoSqkAxuFE603JD2k", "name": "Bobby Rock"}], "availability": {"territories": "AD AR AT AU BE BG BO BR CA CH CL CO CR CY CZ DE DK DO EC EE ES FI FR GB GR GT HK HN HR HU IE IS IT LI LT LU LV MC MT MX MY NI NL NO NZ PA PE PH PL PT PY RO SE SG SI SK SV TR TW US UY"}}, {"name": "Thriller musiikki", "popularity": "0", "external-ids": [{"type": "upc", "id": "3661585946649"}], "href": "spotify:album:0PLvvhIW1zQHrNxzMusoHz", "artists": [{"href": "spotify:artist:6mGcashenMVMsC6JoVLWuG", "name": "Thriller Musiikki"}], "availability": {"territories": "AD AR AT AU BE BG BO BR CA CH CL CO CR CY CZ DE DK DO EC EE ES FI FR GB GR GT HK HN HR HU IE IS IT LI LT LU LV MC MT MX MY NI NL NO NZ PA PE PH PL PT PY RO SE SG SI SK SV TR TW US UY"}}, {"name": "Musique thriller", "popularity": "0", "external-ids": [{"type": "upc", "id": "3661585946625"}], "href": "spotify:album:7kWBJXLcJ39klcKcm2sAop", "artists": [{"href": "spotify:artist:49FKEN39USs8coJlKqDBGK", "name": "Musique Thriller"}], "availability": {"territories": "AD AR AT AU BE BG BO BR CA CH CL CO CR CY CZ DE DK DO EC EE ES FI FR GB GR GT HK HN HR HU IE IS IT LI LT LU LV MC MT MX MY NI NL NO NZ PA PE PH PL PT PY RO SE SG SI SK SV TR TW US UY"}}, {"name": "Musica thriller", "popularity": "0", "external-ids": [{"type": "upc", "id": "3661585946618"}], "href": "spotify:album:6n1RamQu2mBE3TxO3AK7af", "artists": [{"href": "spotify:artist:3AX1XbJIZnWA0iTUjm0ET1", "name": "Musica Thriller"}], "availability": {"territories": "AD AR AT AU BE BG BO BR CA CH CL CO CR CY CZ DE DK DO EC EE ES FI FR GB GR GT HK HN HR HU IE IS IT LI LT LU LV MC MT MX MY NI NL NO NZ PA PE PH PL PT PY RO SE SG SI SK SV TR TW US UY"}}, {"name": "Thriller Music", "popularity": "0.01", "external-ids": [{"type": "upc", "id": "3661585946557"}], "href": "spotify:album:0e6Bz5K0r0qgXQer5DhgeG", "artists": [{"href": "spotify:artist:54cl7U8hASjiC3VdfgPVsC", "name": "Thriller Music"}], "availability": {"territories": "AD AR AT AU BE BG BO BR CA CH CL CO CR CY CZ DE DK DO EC EE ES FI FR GB GR GT HK HN HR HU IE IS IT LI LT LU LV MC MT MX MY NI NL NO NZ PA PE PH PL PT PY RO SE SG SI SK SV TR TW US UY"}}, {"name": "Thriller muziek", "popularity": "0", "external-ids": [{"type": "upc", "id": "3661585946632"}], "href": "spotify:album:7cYhsKt72WCaalPYmZsVnU", "artists": [{"href": "spotify:artist:2P7om46I2njpNetqNfa8K7", "name": "Thriller Muziek"}], "availability": {"territories": "AD AR AT AU BE BG BO BR CA CH CL CO CR CY CZ DE DK DO EC EE ES FI FR GB GR GT HK HN HR HU IE IS IT LI LT LU LV MC MT MX MY NI NL NO NZ PA PE PH PL PT PY RO SE SG SI SK SV TR TW US UY"}}, {"name": "Thriller musik", "popularity": "0", "external-ids": [{"type": "upc", "id": "3661585946595"}], "href": "spotify:album:1xKz06DLZHNVrraiyYrDKU", "artists": [{"href": "spotify:artist:3jcHwcnVSnUB9H3Le8fXdI", "name": "Thriller Musik"}], "availability": {"territories": "AD AR AT AU BE BG BO BR CA CH CL CO CR CY CZ DE DK DO EC EE ES FI FR GB GR GT HK HN HR HU IE IS IT LI LT LU LV MC MT MX MY NI NL NO NZ PA PE PH PL PT PY RO SE SG SI SK SV TR TW US UY"}}, {"name": "Thriller", "popularity": "0.14", "external-ids": [{"type": "upc", "id": "3610152957731"}], "href": "spotify:album:287XdV7Udpz7YaHTo7q8qv", "artists": [{"href": "spotify:artist:0CV6hwBwPdOc9EiSyxxRDq", "name": "Speak Low"}], "availability": {"territories": "AD AR AT AU BE BG BO BR CA CH CL CO CR CY CZ DE DK DO EC EE ES FI FR GB GR GT HK HN HR HU IE IS IT LI LT LU LV MC MT MX MY NI NL NO NZ PA PE PH PL PT PY RO SE SG SI SK SV TR TW US UY"}}, {"name": "Thriller", "popularity": "0.13", "external-ids": [{"type": "upc", "id": "5099750442258"}], "href": "spotify:album:5nFyAjVpdHo5wWx9cgg38M", "artists": [{"href": "spotify:artist:3fMbdgg4jU18AjLCKBhRSm", "name": "Michael Jackson"}], "availability": {"territories": "AT"}}, {"name": "Mission - Spiel auf Zeit - Ein Gideon-Crew-Thriller (Gek\u00fcrzte Fassung)", "popularity": "0.28", "external-ids": [{"type": "upc", "id": "884463477483"}], "href": "spotify:album:4bkqvNoofI8XiTOie3C0B6", "artists": [{"href": "spotify:artist:6Mw2776Oo8wDyxXbBlMuaa", "name": "Douglas Preston"}], "availability": {"territories": "AD AR AT AU BE BG BO BR CA CH CL CO CR CY CZ DE DK DO EC EE ES FI FR GB GR GT HK HN HR HU IE IS IT LI LT LU LV MC MT MX MY NI NL NO NZ PA PE PH PL PT PY RO SE SG SI SK SV TR TW US UY"}}, {"name": "Thriller", "popularity": "0.12", "external-ids": [{"type": "upc", "id": "036172943029"}, {"type": "upc", "id": "036172943029"}], "href": "spotify:album:2FlnViodgTKJmSMg0DHMGG", "artists": [{"href": "spotify:artist:2Lhs0asnFQiLuntn3s8p78", "name": "Lambchop"}], "availability": {"territories": "AR AU BO BR CA CL CO CR CY DO EC GT HK HN MX MY NI NZ PA PE PH PY SG SV TR TW US UY"}}, {"name": "Thriller", "popularity": "0.12", "external-ids": [{"type": "upc", "id": "5050580602496"}], "href": "spotify:album:5mgKU3mNSimv1NLExNCjxY", "artists": [{"href": "spotify:artist:2hexq3VeApqigJuTOeCmHh", "name": "Richie Phoe"}], "availability": {"territories": "AD AR AT AU BE BG BO BR CA CH CL CO CR CY CZ DE DK DO EC EE ES FI FR GB GR GT HK HN HR HU IE IS IT LI LT LU LV MC MT MX MY NI NL NO NZ PA PE PH PL PT PY RO SE SG SI SK SV TR TW US UY"}}, {"name": "Hits From Original Thriller", "popularity": "0", "external-ids": [{"type": "upc", "id": "889326129981"}], "href": "spotify:album:0za4s7BTSAY5zidMWibybB", "artists": [{"href": "spotify:artist:30mSh7YPMwIFa7uI6vd5iv", "name": "Original Thriller"}], "availability": {"territories": "AD AR AT AU BE BG BO BR CA CH CL CO CR CY CZ DE DK DO EC EE ES FI FR GB GR GT HK HN HR HU IE IS IT LI LT LU LV MC MT MX MY NI NL NO NZ PA PE PH PL PT PY RO SE SG SI SK SV TR TW US UY"}}, {"name": "Thriller", "popularity": "0.1", "external-ids": [{"type": "upc", "id": "859706968431"}], "href": "spotify:album:1n68HlYqmhwDv8ZGAfKVcw", "artists": [{"href": "spotify:artist:5Ure3b6cjh5Gk29qg82eym", "name": "Halloween"}], "availability": {"territories": "AD AR AT AU BE BG BO BR CA CH CL CO CR CY CZ DE DK DO EC EE ES FI FR GB GR GT HK HN HR HU IE IS IT LI LT LU LV MC MT MX MY NI NL NO NZ PA PE PH PL PT PY RO SE SG SI SK SV TR TW US UY"}}, {"name": "Symphonic Thriller", "popularity": "0.17", "external-ids": [{"type": "upc", "id": "889176397097"}], "href": "spotify:album:5znpH2KG8uyu8R36roCG8j", "artists": [{"href": "spotify:artist:48PeHqSMyqZj5O3Qk37yJY", "name": "Symphonic Pop Orchestra"}], "availability": {"territories": "AD AR AT AU BE BG BO BR CA CH CL CO CR CY CZ DE DK DO EC EE ES FI FR GB GR GT HK HN HR HU IE IS IT LI LT LU LV MC MT MX MY NI NL NO NZ PA PE PH PL PT PY RO SE SG SI SK SV TR TW US UY"}}, {"name": "Thriller", "popularity": "0.09", "external-ids": [{"type": "upc", "id": "4260185961794"}], "href": "spotify:album:2dZM0Iindu862SkKUul9Bk", "artists": [{"href": "spotify:artist:7xfEjDr3c7DIUoW0qf6s0A", "name": "Richard Grey"}], "availability": {"territories": "AD AR AT AU BE BG BO BR CA CH CL CO CR CY CZ DE DK DO EC EE ES FI FR GB GR GT HK HN HR HU IE IS IT LI LT LU LV MC MT MX MY NI NL NO NZ PA PE PH PL PT PY RO SE SG SI SK SV TR TW US UY"}}, {"name": "Thriller", "popularity": "0.09", "external-ids": [{"type": "upc", "id": "8716059005485"}], "href": "spotify:album:23WYCWDX94MGKXE103aBgM", "artists": [{"href": "spotify:artist:0ann7YfYSXOiH3AHSBn4He", "name": "Orgaanklap"}], "availability": {"territories": "AD AR AT AU BE BG BO BR CA CH CL CO CR CY CZ DE DK DO EC EE ES FI FR GB GR GT HK HN HR HU IE IS IT LI LT LU LV MC MT MX MY NI NL NO NZ PA PE PH PL PT PY RO SE SG SI SK SV TR TW US UY"}}, {"name": "Sings Vintage Music", "popularity": "0", "external-ids": [{"type": "upc", "id": "884502111156"}], "href": "spotify:album:4XtrQfOhetwskriJttBdOL", "artists": [{"href": "spotify:artist:3CiY0RnS9K2BLGUMqzqtPa", "name": "Thriller"}], "availability": {"territories": "AD AR AT AU BE BG BO BR CA CH CL CO CR CY CZ DE DK DO EC EE ES FI FR GB GR GT HK HN HR HU IE IS IT LI LT LU LV MC MT MX MY NI NL NO NZ PA PE PH PL PT PY RO SE SG SI SK SV TR TW US UY"}}, {"name": "Thriller Dance (feat. Jahm Force)", "popularity": "0", "external-ids": [{"type": "upc", "id": "700261984544"}], "href": "spotify:album:566QfXHHIxxwPFgf1xK4Zx", "artists": [{"href": "spotify:artist:2GmK4rj0FpstISsynsbLCp", "name": "Thriller X"}], "availability": {"territories": "AD AR AT AU BE BG BO BR CA CH CL CO CR CY CZ DE DK DO EC EE ES FI FR GB GR GT HK HN HR HU IE IS IT LI LT LU LV MC MT MX MY NI NL NO NZ PA PE PH PL PT PY RO SE SG SI SK SV TR TW US UY"}}, {"name": "Thriller", "popularity": "0.07", "external-ids": [{"type": "upc", "id": "859707645065"}], "href": "spotify:album:0Zj7nCv4k9JZSW9xqTZjKC", "artists": [{"href": "spotify:artist:4PRBH61ujBc3VWylX0IGgG", "name": "PT Walkley"}], "availability": {"territories": "AD AR AT AU BE BG BO BR CA CH CL CO CR CY CZ DE DK DO EC EE ES FI FR GB GR GT HK HN HR HU IE IS IT LI LT LU LV MC MT MX MY NI NL NO NZ PA PE PH PL PT PY RO SE SG SI SK SV TR TW US UY"}}, {"name": "Thriller", "popularity": "0.06", "external-ids": [{"type": "upc", "id": "859712082633"}], "href": "spotify:album:4aSb2b0KA6roQALzQbazw9", "artists": [{"href": "spotify:artist:2BqUKBibADI54rpSuLi8NU", "name": "Patax"}], "availability": {"territories": "AD AR AT AU BE BG BO BR CA CH CL CO CR CY CZ DE DK DO EC EE ES FI FR GB GR GT HK HN HR HU IE IS IT LI LT LU LV MC MT MX MY NI NL NO NZ PA PE PH PL PT PY RO SE SG SI SK SV TR TW US UY"}}, {"name": "Thriller", "popularity": "0.01", "external-ids": [{"type": "upc", "id": "00602517528444"}], "href": "spotify:album:3PP4WkmDvNuy608iC4hBoj", "artists": [{"href": "spotify:artist:70e4IgnWAQfPPxKnD9jXDr", "name": "Eddie & The Hot Rods"}], "availability": {"territories": "GB IE"}}, {"name": "Thriller", "popularity": "0", "external-ids": [{"type": "upc", "id": "085365723962"}], "href": "spotify:album:2sMjNhhna4kRSwuljFr5Ox", "artists": [{"href": "spotify:artist:6AVuKSupq14QCPEvNIumqE", "name": "STFU"}], "availability": {"territories": "DK NO SE"}}, {"name": "Thriller", "popularity": "0", "external-ids": [{"type": "upc", "id": "884385813888"}], "href": "spotify:album:2IXFXRVaAegx2rdl6tkS4T", "artists": [{"name": "Various Artists"}], "availability": {"territories": "AD AR AT AU BE BG BO BR CA CH CL CO CR CY CZ DE DK DO EC EE ES FI FR GB GR GT HK HN HR HU IE IS IT LI LT LU LV MC MT MX MY NI NL NO NZ PA PE PH PL PT PY RO SE SG SI SK SV TR TW US UY"}}, {"name": "Thriller", "popularity": "0", "external-ids": [{"type": "upc", "id": "0885014008644"}], "href": "spotify:album:1zArBSdw4CeQDglw3XNKxy", "artists": [{"href": "spotify:artist:5aE1di46N5vpFDXYBgIaCs", "name": "Teardropcity"}], "availability": {"territories": "AD AR AT AU BE BG BO BR CA CH CL CO CR CY CZ DE DK DO EC EE ES FI FR GB GR GT HK HN HR HU IE IS IT LI LT LU LV MC MT MX MY NI NL NO NZ PA PE PH PL PT PY RO SE SG SI SK SV TR TW US UY"}}, {"name": "Thriller", "popularity": "0.01", "external-ids": [{"type": "upc", "id": "3661585121886"}], "href": "spotify:album:5ePTMSX1slzvzNoT6v8sQ7", "artists": [{"href": "spotify:artist:4Po741Np7M2nmU9zdPiEPs", "name": "Rilod"}], "availability": {"territories": "AD AR AT AU BE BG BO BR CA CH CL CO CR CY CZ DE DK DO EC EE ES FI FR GB GR GT HK HN HR HU IE IS IT LI LT LU LV MC MT MX MY NI NL NO NZ PA PE PH PL PT PY RO SE SG SI SK SV TR TW US UY"}}, {"name": "Thriller", "popularity": "0.01", "external-ids": [{"type": "upc", "id": "3661585214212"}], "href": "spotify:album:0HCYHyfteF9uBQwuM4fxD1", "artists": [{"href": "spotify:artist:2wNctgybNpQiLIOyJ7xNlL", "name": "Gianni Gandi"}], "availability": {"territories": "AD AR AT AU BE BG BO BR CA CH CL CO CR CY CZ DE DK DO EC EE ES FI FR GB GR GT HK HN HR HU IE IS IT LI LT LU LV MC MT MX MY NI NL NO NZ PA PE PH PL PT PY RO SE SG SI SK SV TR TW US UY"}}, {"name": "Thriller", "popularity": "0", "external-ids": [{"type": "upc", "id": "3661585255673"}], "href": "spotify:album:0X7u80DEwEEukxLseoxtID", "artists": [{"href": "spotify:artist:3UD1YAYt7HPza6hqT6KUzI", "name": "Vittorino Lavagno"}], "availability": {"territories": "AD AR AT AU BE BG BO BR CA CH CL CO CR CY CZ DE DK DO EC EE ES FI FR GB GR GT HK HN HR HU IE IS IT LI LT LU LV MC MT MX MY NI NL NO NZ PA PE PH PL PT PY RO SE SG SI SK SV TR TW US UY"}}, {"name": "Thriller", "popularity": "0.03", "external-ids": [{"type": "upc", "id": "4250117609719"}], "href": "spotify:album:0Ob5sSSBMvsrVtL1RryISC", "artists": [{"href": "spotify:artist:6AVuKSupq14QCPEvNIumqE", "name": "STFU"}], "availability": {"territories": "AD AR AT AU BE BG BO BR CA CH CL CO CR CY CZ DE DK DO EC ES FI FR GB GR GT HK HN HR HU IE IT LI LU MC MT MX MY NI NL NO NZ PA PE PH PL PT PY RO SE SG SI SK SV TR TW US UY"}}, {"name": "Thriller", "popularity": "0", "external-ids": [{"type": "upc", "id": "7640130852457"}], "href": "spotify:album:1uJJyLtXPdLCUXuAXpV89Y", "artists": [{"href": "spotify:artist:7xfEjDr3c7DIUoW0qf6s0A", "name": "Richard Grey"}], "availability": {"territories": "AT CH DE LI"}}, {"name": "Thriller!", "popularity": "0.04", "external-ids": [{"type": "upc", "id": "775020766822"}], "href": "spotify:album:3V2BuEy6bSqIHTLCm2fWwj", "artists": [{"href": "spotify:artist:5T4t3V1YSnzL8EwEPS0q6N", "name": "The Witches"}], "availability": {"territories": "AD AR AT AU BE BG BO BR CA CH CL CO CR CY CZ DE DK DO EC EE ES FI FR GB GR GT HK HN HR HU IE IS IT LI LT LU LV MC MT MX MY NI NL NO NZ PA PE PH PL PT PY RO SE SG SI SK SV TR TW US UY"}}, {"name": "Thriller", "popularity": "0.01", "external-ids": [{"type": "upc", "id": "825576989821"}], "href": "spotify:album:4ric2vRRkMXkgbszxggwra", "artists": [{"href": "spotify:artist:3Pi0sKP4codlW2QBkOyWao", "name": "The God Damns"}], "availability": {"territories": "AD AR AT AU BE BG BO BR CA CH CL CO CR CY CZ DE DK DO EC EE ES FI FR GB GR GT HK HN HR HU IE IS IT LI LT LU LV MC MT MX MY NI NL NO NZ PA PE PH PL PT PY RO SE SG SI SK SV TR TW US UY"}}, {"name": "Thriller", "popularity": "0", "external-ids": [{"type": "upc", "id": "090204635139"}], "href": "spotify:album:74RzW8GzfXk0cg7EGN7eSn", "artists": [{"href": "spotify:artist:5iA3cYNA6pS29W8iTyLCPr", "name": "Mr. Jayson"}], "availability": {"territories": "AD AR AT AU BE BG BO BR CA CH CL CO CR CY CZ DE DK DO EC EE ES FI FR GB GR GT HK HN HR HU IE IS IT LI LT LU LV MC MT MX MY NI NL NO NZ PA PE PH PL PT PY RO SE SG SI SK SV TR TW US UY"}}, {"name": "Thriller", "popularity": "0.02", "external-ids": [{"type": "upc", "id": "5099708593025"}], "href": "spotify:album:5Ne1SPpiXQqpCZ6pZCRfIM", "artists": [{"href": "spotify:artist:3fMbdgg4jU18AjLCKBhRSm", "name": "Michael Jackson"}], "availability": {"territories": "AT"}}, {"name": "Thriller", "popularity": "0", "external-ids": [{"type": "upc", "id": "884502428025"}], "href": "spotify:album:4bQkYzF9ub3rX5l21xc3aG", "artists": [{"href": "spotify:artist:2agJtjYEUshI1pZX5TyVxp", "name": "The Mortified After School Orchestra"}], "availability": {"territories": "AD AR AT AU BE BG BO BR CA CH CL CO CR CY CZ DE DK DO EC EE ES FI FR GB GR GT HK HN HR HU IE IS IT LI LT LU LV MC MT MX MY NI NL NO NZ PA PE PH PL PT PY RO SE SG SI SK SV TR TW US UY"}}, {"name": "Thriller", "popularity": "0", "external-ids": [{"type": "upc", "id": "4250618712888"}], "href": "spotify:album:0C0Inc1CO30N7fu9TGjAIQ", "artists": [{"href": "spotify:artist:6Tt8fmdOXADwqxAPyznKak", "name": "Thomas Pryce"}], "availability": {"territories": "AD AR AT AU BE BG BO BR CA CH CL CO CR CY CZ DE DK DO EC EE ES FI FR GB GR GT HK HN HR HU IE IS IT LI LT LU LV MC MT MX MY NI NL NO NZ PA PE PH PL PT PY RO SE SG SI SK SV TR TW US UY"}}, {"name": "Thriller", "popularity": "0.02", "external-ids": [{"type": "upc", "id": "884463444287"}], "href": "spotify:album:1uzaUg8I40fo3pcze6hhJj", "artists": [{"href": "spotify:artist:5bbr30H18b65NtyEqaTdqU", "name": "Killer"}], "availability": {"territories": "AD AR AT AU BE BG BO BR CA CH CL CO CR CY CZ DE DK DO EC EE ES FI FR GB GR GT HK HN HR HU IE IS IT LI LT LU LV MC MT MX MY NI NL NO NZ PA PE PH PL PT PY RO SE SG SI SK SV TR TW US UY"}}, {"name": "Thriller", "popularity": "0", "external-ids": [{"type": "upc", "id": "5414582494600"}], "href": "spotify:album:3Lhu9utaac5ThBteC6plUk", "artists": [{"href": "spotify:artist:4yxfOGswXaFqT0zCRtdsZJ", "name": "Freeker5"}], "availability": {"territories": "AD AR AT AU BE BG BO BR CA CH CL CO CR CY CZ DE DK DO EC EE ES FI FR GB GR GT HK HN HR HU IE IS IT LI LT LU LV MC MT MX MY NI NL NO NZ PA PE PH PL PT PY RO SE SG SI SK SV TR TW US UY"}}, {"name": "Thriller", "popularity": "0", "external-ids": [{"type": "upc", "id": "885012014470"}], "href": "spotify:album:2Oht669axuMgbazhUR9gkA", "artists": [{"href": "spotify:artist:7xfEjDr3c7DIUoW0qf6s0A", "name": "Richard Grey"}], "availability": {"territories": "AD AU BE BG CA CR CZ DK DO EE ES FI GB GR GT HK HN HR HU IE IS IT LI LT LU LV MC MT MX MY NI NL NO NZ PA PH PL PT RO SE SG SI SK SV TW US"}}, {"name": "Thriller", "popularity": "0", "external-ids": [{"type": "upc", "id": "090204969753"}], "href": "spotify:album:2dmz4u1RfU67Qk6tWsqi41", "artists": [{"href": "spotify:artist:4Po741Np7M2nmU9zdPiEPs", "name": "Rilod"}], "availability": {"territories": "AT CH DE"}}, {"name": "Thriller", "popularity": "0", "external-ids": [{"type": "upc", "id": "090204635139"}], "href": "spotify:album:0Em47stGsM53YrQ6nm5gQZ", "artists": [{"href": "spotify:artist:5iA3cYNA6pS29W8iTyLCPr", "name": "Mr. Jayson"}], "availability": {"territories": "AD AR AT AU BE BG BO BR CA CH CL CO CR CY CZ DE DK DO EC EE ES FI FR GB GR GT HK HN HR HU IE IS IT LI LT LU LV MC MT MX MY NI NL NO NZ PA PE PH PL PT PY RO SE SG SI SK SV TR TW US UY"}}, {"name": "Thriller", "popularity": "0", "external-ids": [{"type": "upc", "id": "887516131875"}], "href": "spotify:album:1AGUNer2xEalqwiBK9S1c2", "artists": [{"href": "spotify:artist:71DFnogWp6z4viNlxWeB8W", "name": "Shueh-li Ong"}], "availability": {"territories": "AD AR AT AU BE BG BO BR CA CH CL CO CR CY CZ DE DK DO EC EE ES FI FR GB GR GT HK HN HR HU IE IS IT LI LT LU LV MC MT MX MY NI NL NO NZ PA PE PH PL PT PY RO SE SG SI SK SV TR TW US UY"}}, {"name": "Thriller", "popularity": "0", "external-ids": [{"type": "upc", "id": "3610152208161"}], "href": "spotify:album:2TTRfumHcor05l5jv8VIfq", "artists": [{"href": "spotify:artist:2huEcIEconmbMaKloHqsQY", "name": "Bsharry"}], "availability": {"territories": "AD AR AT AU BE BG BO BR CA CH CL CO CR CY CZ DE DK DO EC EE ES FI FR GB GR GT HK HN HR HU IE IS IT LI LT LU LV MC MT MX MY NI NL NO NZ PA PE PH PL PT PY RO SE SG SI SK SV TR TW US UY"}}, {"name": "Thriller", "popularity": "0.02", "external-ids": [{"type": "upc", "id": "9324690038237"}], "href": "spotify:album:3toT9c5dbqqpXkCdplCLtb", "artists": [{"href": "spotify:artist:6faGoLl1K6HJepvytvYScL", "name": "Swoop"}], "availability": {"territories": "AD AR AT AU BE BG BO BR CA CH CL CO CR CY CZ DE DK DO EC EE ES FI FR GB GR GT HK HN HR HU IE IS IT LI LT LU LV MC MT MX MY NI NL NO NZ PA PE PH PL PT PY RO SE SG SI SK SV TR TW US UY"}}, {"name": "Thriller", "popularity": "0", "external-ids": [{"type": "upc", "id": "8033300004883"}], "href": "spotify:album:1nrOwUIPxg2yW7cM6eRXAk", "artists": [{"href": "spotify:artist:6AVuKSupq14QCPEvNIumqE", "name": "STFU"}], "availability": {"territories": "IT"}}, {"name": "Thriller", "popularity": "0.04", "external-ids": [{"type": "upc", "id": "8423646383177"}], "href": "spotify:album:3JkJpt9dqi3dzbjxEmvVWU", "artists": [{"href": "spotify:artist:0FbvYC4iBSX8lhal77I2Le", "name": "Cobra"}], "availability": {"territories": "AD AR AT AU BE BG BO BR CA CH CL CO CR CY CZ DE DK DO EC EE ES FI FR GB GR GT HK HN HR HU IE IS IT LI LT LU LV MC MT MX MY NI NL NO NZ PA PE PH PL PT PY RO SE SG SI SK SV TR TW US UY"}}, {"name": "Thriller", "popularity": "0", "external-ids": [{"type": "upc", "id": "5052653670159"}], "href": "spotify:album:3gwc2cZ16MPuHlqOa46iwu", "artists": [{"href": "spotify:artist:4zXAUaRXIbSQaFz9SpTXI6", "name": "Dmitry Glushkov"}], "availability": {"territories": "AD AR AT AU BE BG BO BR CA CH CL CO CR CY CZ DE DK DO EC EE ES FI FR GB GR GT HK HN HR HU IE IS IT LI LT LU LV MC MT MX MY NI NL NO NZ PA PE PH PL PT PY RO SE SG SI SK SV TR TW US UY"}}, {"name": "Thriller", "popularity": "0", "external-ids": [{"type": "upc", "id": "4582284550021"}], "href": "spotify:album:2JQJiSnztD9MeCvCMbVSTp", "artists": [{"href": "spotify:artist:5DYV2w6uNHAimNBxRs6zMb", "name": "Inhyeok Yeo"}], "availability": {"territories": "AD AR AT AU BE BG BO BR CA CH CL CO CR CY CZ DE DK DO EC EE ES FI FR GB GR GT HK HN HR HU IE IS IT LI LT LU LV MC MT MX MY NI NL NO NZ PA PE PH PL PT PY RO SE SG SI SK SV TR TW US UY"}}, {"name": "Thriller", "popularity": "0.02", "external-ids": [{"type": "upc", "id": "3610154921891"}], "href": "spotify:album:5ZUESym1bCemWUZYyKckae", "artists": [{"href": "spotify:artist:7xfEjDr3c7DIUoW0qf6s0A", "name": "Richard Grey"}], "availability": {"territories": "AD AR AT AU BE BG BO BR CA CH CL CO CR CY CZ DE DK DO EC EE ES FI FR GB GR GT HK HN HR HU IE IS IT LI LT LU LV MC MT MX MY NI NL NO NZ PA PE PH PL PT PY RO SE SG SI SK SV TR TW US UY"}}, {"name": "Thriller", "popularity": "0.03", "external-ids": [{"type": "upc", "id": "5055807345422"}], "href": "spotify:album:5x3pJwRCKbxDz9VpxIjaHt", "artists": [{"href": "spotify:artist:0pZGZADU2S1Vnn7wozTXzX", "name": "Hoodini"}], "availability": {"territories": "AD AR AT AU BE BG BO BR CA CH CL CO CR CY CZ DE DK DO EC EE ES FI FR GB GR GT HK HN HR HU IE IS IT LI LT LU LV MC MT MX MY NI NL NO NZ PA PE PH PL PT PY RO SE SG SI SK SV TR TW US UY"}}, {"name": "Thriller", "popularity": "0", "external-ids": [{"type": "upc", "id": "888174103624"}], "href": "spotify:album:4AwR32Px0HTn0lJqVi6F2V", "artists": [{"href": "spotify:artist:046G8BiYutCuUWiwXyJDux", "name": "Muartet"}], "availability": {"territories": "AD AR AT AU BE BG BO BR CA CH CL CO CR CY CZ DE DK DO EC EE ES FI FR GB GR GT HK HN HR HU IE IS IT LI LT LU LV MC MT MX MY NI NL NO NZ PA PE PH PL PT PY RO SE SG SI SK SV TR TW US UY"}}, {"name": "Thriller", "popularity": "0", "external-ids": [{"type": "upc", "id": "0816152017601"}], "href": "spotify:album:7lCkERXcSmYFcYBPP7nxkI", "artists": [{"href": "spotify:artist:3cqzvV8NiNhCernhxcqSr4", "name": "Jack Di'Che"}], "availability": {"territories": "AD AR AT AU BE BG BO BR CA CH CL CO CR CY CZ DE DK DO EC EE ES FI FR GB GR GT HK HN HR HU IE IS IT LI LT LU LV MC MT MX MY NI NL NO NZ PA PE PH PL PT PY RO SE SG SI SK SV TR TW US UY"}}, {"name": "Thriller", "popularity": "0", "external-ids": [{"type": "upc", "id": "3610156331209"}], "href": "spotify:album:5E1p91qnwYh0inxGEB9RBY", "artists": [{"href": "spotify:artist:6FAcudQV3YzqrtlZdbTt8q", "name": "Kamses"}], "availability": {"territories": "AD AR AT AU BE BG BO BR CA CH CL CO CR CY CZ DE DK DO EC EE ES FI FR GB GR GT HK HN HR HU IE IS IT LI LT LU LV MC MT MX MY NI NL NO NZ PA PE PH PL PT PY RO SE SG SI SK SV TR TW US UY"}}, {"name": "Thriller", "popularity": "0", "external-ids": [{"type": "upc", "id": "3700735804276"}], "href": "spotify:album:0f14cUmVyKHIexzHAH7OXR", "artists": [{"href": "spotify:artist:64BmuqNotB5zDlrI4lDiRC", "name": "D.O.U"}], "availability": {"territories": "AD AR AT AU BE BG BO BR CA CH CL CO CR CY CZ DE DK DO EC EE ES FI FR GB GR GT HK HN HR HU IE IS IT LI LT LU LV MC MT MX MY NI NL NO NZ PA PE PH PL PT PY RO SE SG SI SK SV TR TW US UY"}}, {"name": "Thriller", "popularity": "0", "external-ids": [{"type": "upc", "id": "5054281145078"}], "href": "spotify:album:2KExRo5fN5I3ksXqZOdJB4", "artists": [{"href": "spotify:artist:3xKGhixeP24bKwHQ7yPyXF", "name": "Joey Riot"}], "availability": {"territories": "AD AR AT AU BE BG BO BR CA CH CL CO CR CY CZ DE DK DO EC EE ES FI FR GB GR GT HK HN HR HU IE IS IT LI LT LU LV MC MT MX MY NI NL NO NZ PA PE PH PL PT PY RO SE SG SI SK SV TR TW US UY"}}, {"name": "Thriller", "popularity": "0", "external-ids": [{"type": "upc", "id": "0827170349087"}], "href": "spotify:album:7iysAv3beKZjAWahMwDuRf", "artists": [{"href": "spotify:artist:0aZZV7jkpBvDHFQHlV7MWO", "name": "John Hughes Daydream"}], "availability": {"territories": "AD AR AT AU BE BG BO BR CA CH CL CO CR CY CZ DE DK DO EC EE ES FI FR GB GR GT HK HN HR HU IE IS IT LI LT LU LV MC MT MX MY NI NL NO NZ PA PE PH PL PT PY RO SE SG SI SK SV TR TW US UY"}}, {"name": "Thriller", "popularity": "0", "external-ids": [{"type": "upc", "id": "3610158518370"}], "href": "spotify:album:3J5LuPZSJY3NIea0i8msnw", "artists": [{"href": "spotify:artist:7zcVKlkwqRQ3kuZNt4LrFf", "name": "Monsieur"}], "availability": {"territories": "AD AR AT AU BE BG BO BR CA CH CL CO CR CY CZ DE DK DO EC EE ES FI FR GB GR GT HK HN HR HU IE IS IT LI LT LU LV MC MT MX MY NI NL NO NZ PA PE PH PL PT PY RO SE SG SI SK SV TR TW US UY"}}, {"name": "Thriller", "popularity": "0", "external-ids": [{"type": "upc", "id": "5054316867104"}], "href": "spotify:album:6tbDNNga9AUDnzvLwMI9aq", "artists": [{"href": "spotify:artist:1H0b3ecXfJE5Slbeq0FnVI", "name": "Tetis"}], "availability": {"territories": "AD AR AT AU BE BG BO BR CA CH CL CO CR CY CZ DE DK DO EC EE ES FI FR GB GR GT HK HN HR HU IE IS IT LI LT LU LV MC MT MX MY NI NL NO NZ PA PE PH PL PT PY RO SE SG SI SK SV TR TW US UY"}}, {"name": "Thriller", "popularity": "0", "external-ids": [{"type": "upc", "id": "5055946753898"}], "href": "spotify:album:4UaFkzF1soQJglHqPgRxnu", "artists": [{"href": "spotify:artist:7BXqItaPWdlzngmuqmsZKt", "name": "Pantogran"}], "availability": {"territories": "AD AR AT AU BE BG BO BR CA CH CL CO CR CY CZ DE DK DO EC EE ES FI FR GB GR GT HK HN HR HU IE IS IT LI LT LU LV MC MT MX MY NI NL NO NZ PA PE PH PL PT PY RO SE SG SI SK SV TR TW US UY"}}, {"name": "Thriller", "popularity": "0", "external-ids": [{"type": "upc", "id": "853564359066"}], "href": "spotify:album:6IT2eWSaI49TSfXaQul8xA", "artists": [{"href": "spotify:artist:4ChTvCgb12ZXQ0yEPAjWIP", "name": "Max Rogue"}], "availability": {"territories": "AD AR AT AU BE BG BO BR CA CH CL CO CR CY CZ DE DK DO EC EE ES FI FR GB GR GT HK HN HR HU IE IS IT LI LT LU LV MC MT MX MY NI NL NO NZ PA PE PH PL PT PY RO SE SG SI SK SV TR TW US UY"}}, {"name": "Thriller", "popularity": "0", "external-ids": [{"type": "upc", "id": "5054281706682"}], "href": "spotify:album:1uWNHOdlgJ64OZF7KRxmYN", "artists": [{"href": "spotify:artist:6wdU7edClFgPizoTR1WVh7", "name": "Korioto"}], "availability": {"territories": "AD AR AT AU BE BG BO BR CA CH CL CO CR CY CZ DE DK DO EC EE ES FI FR GB GR GT HK HN HR HU IE IS IT LI LT LU LV MC MT MX MY NI NL NO NZ PA PE PH PL PT PY RO SE SG SI SK SV TR TW US UY"}}, {"name": "Thriller", "popularity": "0", "external-ids": [{"type": "upc", "id": "634479227394"}], "href": "spotify:album:7DY43PtxqqrtRwiNuaeMqH", "artists": [{"href": "spotify:artist:4oM5NZ8NQ3CLLAjZGbjwYI", "name": "Four Peace Island"}], "availability": {"territories": "AD AR AT AU BE BG BO BR CA CH CL CO CR CY CZ DE DK DO EC EE ES FI FR GB GR GT HK HN HR HU IE IS IT LI LT LU LV MC MT MX MY NI NL NO NZ PA PE PH PL PT PY RO SE SG SI SK SV TR TW US UY"}}, {"name": "Thriller", "popularity": "0", "external-ids": [{"type": "upc", "id": "5055946797236"}], "href": "spotify:album:5c57Ztr08k3JKVUmOuAkfM", "artists": [{"href": "spotify:artist:0dmK5swyEcHMHK570klgLx", "name": "Gabriel Marchisio"}], "availability": {"territories": "AD AR AT AU BE BG BO BR CA CH CL CO CR CY CZ DE DK DO EC EE ES FI FR GB GR GT HK HN HR HU IE IS IT LI LT LU LV MC MT MX MY NI NL NO NZ PA PE PH PL PT PY RO SE SG SI SK SV TR TW US UY"}}, {"name": "Cinematic Action Thriller", "popularity": "0.17", "external-ids": [{"type": "upc", "id": "840080152653"}], "href": "spotify:album:0w5r6YxHIkvBVc3FFCacOU", "artists": [{"href": "spotify:artist:4Y9OsiVeej2SP674qNjFV1", "name": "LiquidCinema"}], "availability": {"territories": "AD AR AT AU BE BG BO BR CA CH CL CO CR CY CZ DE DK DO EC EE ES FI FR GB GR GT HK HN HR HU IE IS IT LI LT LU LV MC MT MX MY NI NL NO NZ PA PE PH PL PT PY RO SE SG SI SK SV TR TW US UY"}}, {"name": "Action\/Thriller 4 - Film Trailer Music", "popularity": "0.21", "external-ids": [{"type": "upc", "id": "886788239906"}], "href": "spotify:album:5SIWXjeV6WBLwzI7o3RKjp", "artists": [{"href": "spotify:artist:0V242PM3QFALRmtAjF7S9U", "name": "Lorenzo Piggici & Jochen Flach"}], "availability": {"territories": "AD AR AT AU BE BG BO BR CA CH CL CO CR CY CZ DE DK DO EC EE ES FI FR GB GR GT HK HN HR HU IE IS IT LI LT LU LV MC MT MX MY NI NL NO NZ PA PE PH PL PT PY RO SE SG SI SK SV TR TW US UY"}}, {"name": "Thriller \/ Hank", "popularity": "0.1", "external-ids": [{"type": "upc", "id": "4250506812683"}], "href": "spotify:album:3lBrxusDxlY8utCrghjKDf", "artists": [{"href": "spotify:artist:2Lhs0asnFQiLuntn3s8p78", "name": "Lambchop"}], "availability": {"territories": "GB IE"}}, {"name": "Reggae One Drop Volume 01", "popularity": "0.1", "external-ids": [{"type": "upc", "id": "660662491921"}], "href": "spotify:album:4QQfAfJto4Vc6J1LZVvg4o", "artists": [{"href": "spotify:artist:4u7M5tR2mWLhoKGxjJsz1V", "name": "Thriller U"}], "availability": {"territories": "AD AR AT AU BE BG BO BR CA CH CL CO CR CY CZ DE DK DO EC EE ES FI FR GB GR GT HK HN HR HU IE IS IT LI LT LU LV MC MT MX MY NI NL NO NZ PA PE PH PL PT PY RO SE SG SI SK SV TR TW US UY"}}, {"name": "The Very Best", "popularity": "0.11", "external-ids": [{"type": "upc", "id": "695831280327"}], "href": "spotify:album:0Q68WrCDP2w1COPX0r4Cpl", "artists": [{"href": "spotify:artist:4u7M5tR2mWLhoKGxjJsz1V", "name": "Thriller U"}], "availability": {"territories": "AD AR AT AU BE BG BO BR CA CH CL CO CR CY CZ DE DK DO EC EE ES FI FR GB GR GT HK HN HR HU IE IS IT LI LT LU LV MC MT MX MY NI NL NO NZ PA PE PH PL PT PY RO SE SG SI SK SV TR TW US UY"}}, {"name": "Thriller\/ Hank", "popularity": "0.08", "external-ids": [{"type": "upc", "id": "884463150423"}], "href": "spotify:album:70tbAJGLfqdhXPAfQ1VlTn", "artists": [{"href": "spotify:artist:2Lhs0asnFQiLuntn3s8p78", "name": "Lambchop"}], "availability": {"territories": "AT CH DE"}}, {"name": "Thriller 2", "popularity": "0.06", "external-ids": [{"type": "upc", "id": "859706266599"}], "href": "spotify:album:2ZdgHN2o314Inh5JHaw40h", "artists": [{"href": "spotify:artist:4l39dbDzEoSESkKoOnVPio", "name": "Rocket Me Nowhere"}], "availability": {"territories": "AD AR AT AU BE BG BO BR CA CH CL CO CR CY CZ DE DK DO EC EE ES FI FR GB GR GT HK HN HR HU IE IS IT LI LT LU LV MC MT MX MY NI NL NO NZ PA PE PH PL PT PY RO SE SG SI SK SV TR TW US UY"}}, {"name": "Thriller \/ Hank", "popularity": "0.05", "external-ids": [{"type": "upc", "id": "4250506804206"}], "href": "spotify:album:7zLqUSPXEO7wf97EizcbQl", "artists": [{"href": "spotify:artist:2Lhs0asnFQiLuntn3s8p78", "name": "Lambchop"}], "availability": {"territories": "AR BG BO BR CA CL CO CR DO EC FR GT HK HN HU LT LV MY NI PA PE PH PL PY RO SG SV TR TW UY"}}, {"name": "Popcorn Thriller", "popularity": "0.06", "external-ids": [{"type": "upc", "id": "859714058803"}], "href": "spotify:album:0YROlRT9tftAxzBjJXOgY1", "artists": [{"href": "spotify:artist:2iyTQD4n0K3rIFdsXVLZWB", "name": "Maxed Out"}], "availability": {"territories": "AD AR AT AU BE BG BO BR CA CH CL CO CR CY CZ DE DK DO EC EE ES FI FR GB GR GT HK HN HR HU IE IS IT LI LT LU LV MC MT MX MY NI NL NO NZ PA PE PH PL PT PY RO SE SG SI SK SV TR TW US UY"}}, {"name": "Abw\u00e4rts - Ein Thriller H\u00f6rspiel", "popularity": "0.16", "external-ids": [{"type": "upc", "id": "4001617070727"}], "href": "spotify:album:5YS9fZi4w2nzICS5tYXx4D", "artists": [{"href": "spotify:artist:0pMFtBeDPPJUwmtGoUROK2", "name": "Frank G\u00f6hre"}], "availability": {"territories": "AD AR AT AU BE BG BO BR CA CH CL CO CR CY CZ DE DK DO EC EE ES FI FR GB GR GT HK HN HR HU IE IS IT LI LT LU LV MC MT MX MY NI NL NO NZ PA PE PH PL PT PY RO SE SG SI SK SV TR TW US UY"}}, {"name": "Love Rule", "popularity": "0.05", "external-ids": [{"type": "upc", "id": "054645143967"}], "href": "spotify:album:23Bjd6A3UozqCRyCcYxkZa", "artists": [{"href": "spotify:artist:4u7M5tR2mWLhoKGxjJsz1V", "name": "Thriller U"}], "availability": {"territories": "AD AR AT AU BE BG BO BR CA CH CL CO CR CY CZ DE DK DO EC EE ES FI FR GB GR GT HK HN HR HU IE IS IT LI LT LU LV MC MT MX MY NI NL NO NZ PA PE PH PL PT PY RO SE SG SI SK SV TR TW US UY"}}, {"name": "The Original Thriller", "popularity": "0.1", "external-ids": [{"type": "upc", "id": "5017447610056"}], "href": "spotify:album:0r31RLJDrNYmMIYCHde6je", "artists": [{"href": "spotify:artist:5WwEQwX3ruZofwDDqtOXwI", "name": "Augustus Pablo"}], "availability": {"territories": "AD AR AT AU BE BG BO BR CA CH CL CO CR CY CZ DE DK DO EC EE ES FI FR GB GR GT HK HN HR HU IE IS IT LI LT LU LV MC MT MX MY NI NL NO NZ PA PE PH PL PT PY RO SE SG SI SK SV TR TW US UY"}}, {"name": "Thriller (Funky Version)", "popularity": "0.11", "external-ids": [{"type": "upc", "id": "859713532465"}], "href": "spotify:album:3dEtLSZSsnNBSFSMasCPBD", "artists": [{"href": "spotify:artist:2BqUKBibADI54rpSuLi8NU", "name": "Patax"}], "availability": {"territories": "AD AR AT AU BE BG BO BR CA CH CL CO CR CY CZ DE DK DO EC EE ES FI FR GB GR GT HK HN HR HU IE IS IT LI LT LU LV MC MT MX MY NI NL NO NZ PA PE PH PL PT PY RO SE SG SI SK SV TR TW US UY"}}, {"name": "Stereo Thriller", "popularity": "0", "external-ids": [{"type": "upc", "id": "803680567326"}], "href": "spotify:album:2AK1psfBKgJRjqPNXhsYoO", "artists": [{"href": "spotify:artist:6pMwLPCeVozirbLZr88e7a", "name": "Joey Kingpin"}], "availability": {"territories": "AD AR AT AU BE BG BO BR CA CH CL CO CR CY CZ DE DK DO EC EE ES FI FR GB GR GT HK HN HR HU IE IS IT LI LT LU LV MC MT MX MY NI NL NO NZ PA PE PH PL PT PY RO SE SG SI SK SV TR TW US UY"}}, {"name": "Piller \/ Thriller", "popularity": "0", "external-ids": [{"type": "upc", "id": "3661585115229"}], "href": "spotify:album:1nzjuvg9NmnQcMnlH1eXZE", "artists": [{"href": "spotify:artist:189aZgqac0fpuq6i8gcTrM", "name": "Oliver Deutschmann"}], "availability": {"territories": "AD AR AT AU BE BG BO BR CA CH CL CO CR CY CZ DE DK DO EC EE ES FI FR GB GR GT HK HN HR HU IE IS IT LI LT LU LV MC MT MX MY NI NL NO NZ PA PE PH PL PT PY RO SE SG SI SK SV TR TW US UY"}}, {"name": "Thriller klingelt\u00f6ne", "popularity": "0", "external-ids": [{"type": "upc", "id": "3661585874492"}], "href": "spotify:album:7gGpIBsp0xf65uNzzlo1qY", "artists": [{"href": "spotify:artist:0J0by55Qlgr1QUcBnYDMSN", "name": "Klingelt\u00f6ne"}], "availability": {"territories": "AD AR AT AU BE BG BO BR CA CH CL CO CR CY CZ DE DK DO EC EE ES FI FR GB GR GT HK HN HR HU IE IS IT LI LT LU LV MC MT MX MY NI NL NO NZ PA PE PH PL PT PY RO SE SG SI SK SV TR TW US UY"}}, {"name": "Thriller ringetoner", "popularity": "0", "external-ids": [{"type": "upc", "id": "3661585874522"}], "href": "spotify:album:2rIbbPsWORHK2Q3sMSFtsJ", "artists": [{"href": "spotify:artist:766hpKZeU1aOviUbfkl1LG", "name": "Ringetoner"}], "availability": {"territories": "AD AR AT AU BE BG BO BR CA CH CL CO CR CY CZ DE DK DO EC EE ES FI FR GB GR GT HK HN HR HU IE IS IT LI LT LU LV MC MT MX MY NI NL NO NZ PA PE PH PL PT PY RO SE SG SI SK SV TR TW US UY"}}, {"name": "Suoneria thriller", "popularity": "0", "external-ids": [{"type": "upc", "id": "3661585874485"}], "href": "spotify:album:5RZRzysFcR113bLxvCP6qZ", "artists": [{"href": "spotify:artist:1HiGfgevFjPnXRpTBp0Yi6", "name": "Suonerie per cellulari"}], "availability": {"territories": "AD AR AT AU BE BG BO BR CA CH CL CO CR CY CZ DE DK DO EC EE ES FI FR GB GR GT HK HN HR HU IE IS IT LI LT LU LV MC MT MX MY NI NL NO NZ PA PE PH PL PT PY RO SE SG SI SK SV TR TW US UY"}}, {"name": "Thriller sonnerie", "popularity": "0", "external-ids": [{"type": "upc", "id": "3661585875031"}], "href": "spotify:album:2q6yG93ux0czPBpNiEajMd", "artists": [{"href": "spotify:artist:3mBoIxf2lXHK09sgbaeOPc", "name": "Sonneries portable"}], "availability": {"territories": "AD AR AT AU BE BG BO BR CA CH CL CO CR CY CZ DE DK DO EC EE ES FI FR GB GR GT HK HN HR HU IE IS IT LI LT LU LV MC MT MX MY NI NL NO NZ PA PE PH PL PT PY RO SE SG SI SK SV TR TW US UY"}}]}